nothing/__init__.py
nothing_anwarvic-1.0.2.dist-info/LICENSE
nothing_anwarvic-1.0.2.dist-info/METADATA
nothing_anwarvic-1.0.2.dist-info/WHEEL
nothing_anwarvic-1.0.2.dist-info/top_level.txt
nothing_anwarvic-1.0.2.dist-info/RECORD
