Metadata-Version: 2.1
Name: nothing-anwarvic
Version: 1.0.2
Summary: Nothing.. just nothing!
Home-page: https://github.com/Anwarvic/nothing
Author: Anwarvic
Author-email: mohamedanwarvic@gmail.com
License: UNKNOWN
Platform: UNKNOWN
Classifier: Programming Language :: Python :: 3
Classifier: License :: OSI Approved :: MIT License
Classifier: Operating System :: OS Independent
Requires-Python: >=3.6
